varstool/__init__.py
varstool/varstool.py
varstool/example_models/__init__.py
varstool/example_models/hbv.py
varstool/example_models/sample_funcs.py
varstool/example_models/banff/__init__.py
varstool/example_models/oldman/__init__.py
varstool/sampling/__init__.py
varstool/sampling/g_starvars.py
varstool/sampling/halton.py
varstool/sampling/lhs.py
varstool/sampling/plhs.py
varstool/sampling/sobol_sequence.py
varstool/sampling/starvars.py
varstool/sampling/symlhs.py
varstool/sensitivity_analysis/__init__.py
varstool/sensitivity_analysis/dvars_funcs.py
varstool/sensitivity_analysis/gvars_funcs.py
varstool/sensitivity_analysis/tsgvars_funcs.py
varstool/sensitivity_analysis/tsvars_funcs.py
varstool/sensitivity_analysis/vars_funcs.py
varstool-2.3.5.dist-info/LICENSE
varstool-2.3.5.dist-info/METADATA
varstool-2.3.5.dist-info/WHEEL
varstool-2.3.5.dist-info/top_level.txt
varstool-2.3.5.dist-info/RECORD
