Metadata-Version: 2.1
Name: varstool
Version: 2.3.5
Summary: VARS-TOOL Sensitivity and Uncertainty Analysis Package
Home-page: https://www.vars-tool.com
Author: Saman Razavi, Kasra Keshavarz, Cordell Blanchard
Author-email: saman.razavi@usask.ca, kasra.keshavarz@usask.ca, cordell.blanchard@usask.ca
License: gpl3
Project-URL: Bug Tracker, https://github.com/vars-tool/vars-tool/issues
Project-URL: Documentation, https://vars-tool.readthedocs.io/en/latest/index.html
Project-URL: Source Code, https://github.com/vars-tool/vars-tool
Platform: any
Classifier: Development Status :: 5 - Production/Stable
Classifier: Programming Language :: Python :: 3
Classifier: Programming Language :: Python :: 3.7
Classifier: Programming Language :: Python :: 3.8
Classifier: Programming Language :: Python :: 3.9
Classifier: Programming Language :: Python :: 3.10
Classifier: License :: OSI Approved :: GNU General Public License v3 (GPLv3)
Classifier: Intended Audience :: Education
Classifier: Topic :: Scientific/Engineering
Classifier: Operating System :: OS Independent
Requires-Python: >=3.7
License-File: LICENSE
Requires-Dist: numpy
Requires-Dist: scipy
Requires-Dist: matplotlib
Requires-Dist: pandas
Requires-Dist: mapply
Requires-Dist: psutil
Requires-Dist: joblib
Requires-Dist: tqdm
